.gitignore
setup.py
ebs/__init__.py
ebs/linuxnode/__init__.py
ebs/linuxnode/gallery/__init__.py
ebs/linuxnode/gallery/constants.py
ebs/linuxnode/gallery/managers.py
ebs/linuxnode/gallery/mixin.py
ebs/linuxnode/gallery/models.py
ebs/linuxnode/gallery/resources.py
ebs/linuxnode/gui/__init__.py
ebs/linuxnode/gui/kivy/__init__.py
ebs/linuxnode/gui/kivy/gallery/__init__.py
ebs/linuxnode/gui/kivy/gallery/mixin.py
ebs_linuxnode_gui_kivy_gallery.egg-info/PKG-INFO
ebs_linuxnode_gui_kivy_gallery.egg-info/SOURCES.txt
ebs_linuxnode_gui_kivy_gallery.egg-info/dependency_links.txt
ebs_linuxnode_gui_kivy_gallery.egg-info/requires.txt
ebs_linuxnode_gui_kivy_gallery.egg-info/top_level.txt