Metadata-Version: 2.1
Name: ebs-linuxnode-gui-kivy-gallery
Version: 2.2
Summary: Image Gallery infrastructure linuxnode applications
Home-page: https://github.com/ebs-universe/ebs-linuxnode-kivy-gallery
Author: Chintalagiri Shashank
Author-email: shashank.chintalagiri@gmail.com
Classifier: Development Status :: 5 - Production/Stable
Classifier: Intended Audience :: Developers
Classifier: License :: OSI Approved :: GNU General Public License v3 or later (GPLv3+)
Classifier: Programming Language :: Python
Classifier: Programming Language :: Python :: 3
Classifier: Programming Language :: Python :: 3.6
Classifier: Operating System :: POSIX :: Linux
